{
    "summary": "Retrive an existing departement by id",
    "description": "Retrieve an existing departement by its unique identifier.",
    "operationId": "getDepartement",
    "parameters": [
        {
            "$ref": "../../components/parameters/departement_id.json#/DepartementId"
        },
        {
            "name": "fields",
            "in": "query",
            "description": "Comma-separated list of fields to include in the response.",
            "required": false,
            "schema": {
                "type": "string"
            },
            "example": "id,name"
        },
        {
            "$ref": "../../components/headers/content_type.json"
        },
        {
            "$ref": "../../components/headers/accept.json"
        },
        {
            "$ref": "../../components/headers/origin.json"
        }
    ],
    "responses": {
        "200": {
            "description": "Successfully retrieved departement",
            "headers": {
                "X-RateLimit-Limit": {
                    "$ref": "../../components/headers/x_ratelimit_limit.json"
                },
                "X-RateLimit-Remaining": {
                    "$ref": "../../components/headers/x_ratelimit_remaining.json"
                },
                "Access-Control-Allow-Origin": {
                    "$ref": "../../components/headers/access_control_allow_origin.json"
                },
                "Access-Control-Allow-Methods": {
                    "$ref": "../../components/headers/access_control_allow_methods.json"
                },
                "Access-Control-Allow-Credentials": {
                    "$ref": "../../components/headers/access_control_allow_credentials.json"
                },
                "Access-Control-Max-Age": {
                    "$ref": "../../components/headers/access_control_max_age.json"
                },
                "Access-Control-Allow-Headers": {
                    "$ref": "../../components/headers/access_control_allow_headers.json"
                }
            },
            "content": {
                "application/json": {
                    "schema": {
                        "type": "object",
                        "properties": {
                            "status": {
                                "type": "boolean",
                                "description": "Indicates the success status of the request.",
                                "default": true,
                                "example": true
                            },
                            "message": {
                                "type": "string",
                                "description": "Additional information about the response.",
                                "default": "Departement retrieved successfully",
                                "example": "Departement retrieved successfully"
                            },
                            "data": {
                                "$ref": "../../components/schemas/models/departement.json#/Departement"
                            },
                            "status_code": {
                                "type": "integer",
                                "description": "Indicates the HTTP status code of the response.",
                                "default": 200,
                                "example": 200
                            }
                        }
                    }
                }
            },
            "links": {
                "UpdateDepartementDetailsByDepartementId": {
                    "operationId": "updateDepartement",
                    "parameters": {
                        "departementId": "$response.body#/data/id"
                    },
                    "description": "Link to update departement information based on departement ID."
                },
                "DeleteDepartementByDepartementId": {
                    "operationId": "deleteDepartement",
                    "parameters": {
                        "departementId": "$response.body#/data/id"
                    },
                    "description": "Link to delete departement based on departement ID."
                }
            }
        },
        "400": {
            "$ref": "../../components/responses/errors/400.json#BadRequest"
        },
        "401": {
            "$ref": "../../components/responses/errors/401.json#Unauthorized"
        },
        "403": {
            "$ref": "../../components/responses/errors/403.json#Forbidden"
        },
        "404": {
            "$ref": "../../components/responses/errors/404.json#NotFound"
        },
        "405": {
            "$ref": "../../components/responses/errors/405.json#MethodNotAllowed"
        },
        "408": {
            "$ref": "../../components/responses/errors/408.json#RequestTimeout"
        },
        "429": {
            "$ref": "../../components/responses/errors/429.json#RateLimitExceeded"
        },
        "500": {
            "$ref": "../../components/responses/errors/500.json#InternalServerError"
        },
        "503": {
            "$ref": "../../components/responses/errors/503.json#ServiceUnavailable"
        }
    }
}